Python3CookbookZhongwenban/README.md
Python3CookbookZhongwenban/__init__.py
Python3CookbookZhongwenban/__main__.py
Python3CookbookZhongwenban/file.epub
Python3CookbookZhongwenban/index.html
Python3CookbookZhongwenban/css/__init__.py
Python3CookbookZhongwenban/css/annotations.css
Python3CookbookZhongwenban/css/main.css
Python3CookbookZhongwenban/css/normalize.css
Python3CookbookZhongwenban/css/popup.css
Python3CookbookZhongwenban/font/__init__.py
Python3CookbookZhongwenban/font/fontello.eot
Python3CookbookZhongwenban/font/fontello.svg
Python3CookbookZhongwenban/font/fontello.ttf
Python3CookbookZhongwenban/font/fontello.woff
Python3CookbookZhongwenban/img/__init__.py
Python3CookbookZhongwenban/img/annotator-glyph-sprite.png
Python3CookbookZhongwenban/img/annotator-icon-sprite.png
Python3CookbookZhongwenban/img/apple-touch-icon.png
Python3CookbookZhongwenban/img/cancelfullscreen.png
Python3CookbookZhongwenban/img/close.png
Python3CookbookZhongwenban/img/fullscreen.png
Python3CookbookZhongwenban/img/loader.gif
Python3CookbookZhongwenban/img/menu-icon.png
Python3CookbookZhongwenban/img/save.png
Python3CookbookZhongwenban/img/saved.png
Python3CookbookZhongwenban/img/settings-s.png
Python3CookbookZhongwenban/img/settings.png
Python3CookbookZhongwenban/img/star.png
Python3CookbookZhongwenban/js/__init__.py
Python3CookbookZhongwenban/js/epub.js
Python3CookbookZhongwenban/js/epub.min.js
Python3CookbookZhongwenban/js/epub.min.map
Python3CookbookZhongwenban/js/hooks.min.js
Python3CookbookZhongwenban/js/hooks.min.map
Python3CookbookZhongwenban/js/reader.js
Python3CookbookZhongwenban/js/reader.js.map
Python3CookbookZhongwenban/js/reader.min.js
Python3CookbookZhongwenban/js/reader.min.map
Python3CookbookZhongwenban/js/hooks/__init__.py
Python3CookbookZhongwenban/js/hooks/extensions/__init__.py
Python3CookbookZhongwenban/js/hooks/extensions/highlight.js
Python3CookbookZhongwenban/js/libs/__init__.py
Python3CookbookZhongwenban/js/libs/jquery.min.js
python3_cookbook_zhongwenban-2024.3.1.0.dist-info/METADATA
python3_cookbook_zhongwenban-2024.3.1.0.dist-info/WHEEL
python3_cookbook_zhongwenban-2024.3.1.0.dist-info/entry_points.txt
python3_cookbook_zhongwenban-2024.3.1.0.dist-info/top_level.txt
python3_cookbook_zhongwenban-2024.3.1.0.dist-info/RECORD
